setup.py
quamotion/__init__.py
quamotion.egg-info/PKG-INFO
quamotion.egg-info/SOURCES.txt
quamotion.egg-info/dependency_links.txt
quamotion.egg-info/not-zip-safe
quamotion.egg-info/requires.txt
quamotion.egg-info/top_level.txt