Metadata-Version: 1.0
Name: quamotion
Version: 0.62.2
Summary: Python client for the Quamotion WebDriver
Home-page: http://github.com/quamotion/python
Author: Quamotion
Author-email: info@quamotion.mobi
License: Apache
Platform: UNKNOWN
